ebdalia-0.1.5.data/scripts/ebdalia
objects/__init__.py
objects/exceptions.py
ebdalia-0.1.5.dist-info/METADATA
ebdalia-0.1.5.dist-info/WHEEL
ebdalia-0.1.5.dist-info/top_level.txt
ebdalia-0.1.5.dist-info/RECORD
