Metadata-Version: 2.1
Name: ebdalia
Version: 0.1.5
Summary: Elastic Beanstalk ssh cli using the internal IP address
Home-page: https://github.com/DaliaResearch/ebdalia
Author: Jonathas Hortense
Author-email: jonathas.hortense@daliaresearch.com
License: UNKNOWN
Platform: UNKNOWN
Requires-Dist: awsebcli
Requires-Dist: boto3
